Metadata-Version: 1.0
Name: celery-with-redis
Version: 2.4
Summary: Bundle that installs the dependencies for Celery and Redis
Home-page: http://celeryproject.org
Author: Celery Project
Author-email: bundles@celeryproject.org
License: BSD
Platform: all
Classifier: Topic :: Software Development :: Libraries :: Python Modules
